CHANGES.rst
MANIFEST.in
README.rst
setup.py
invisibleroads_repositories/__init__.py
invisibleroads_repositories/exceptions.py
invisibleroads_repositories/github.py
invisibleroads_repositories.egg-info/PKG-INFO
invisibleroads_repositories.egg-info/SOURCES.txt
invisibleroads_repositories.egg-info/dependency_links.txt
invisibleroads_repositories.egg-info/not-zip-safe
invisibleroads_repositories.egg-info/requires.txt
invisibleroads_repositories.egg-info/top_level.txt