Metadata-Version: 1.1
Name: invisibleroads-repositories
Version: 0.1.3
Summary: Functions for managing code repositories
Home-page: http://invisibleroads.com
Author: Roy Hyunjin Han
Author-email: rhh@crosscompute.com
License: UNKNOWN
Keywords: invisibleroads
Platform: UNKNOWN
Classifier: Programming Language :: Python
Classifier: License :: OSI Approved :: MIT License
